szyfrow/__init__.py
szyfrow/affine.py
szyfrow/amsco.py
szyfrow/autokey.py
szyfrow/bifid.py
szyfrow/bombe.py
szyfrow/cadenus.py
szyfrow/caesar.py
szyfrow/column_transposition.py
szyfrow/enigma.py
szyfrow/hill.py
szyfrow/keyword_cipher.py
szyfrow/playfair.py
szyfrow/pocket_enigma.py
szyfrow/polybius.py
szyfrow/railfence.py
szyfrow/vigenere.py
szyfrow/language_model_files/__init__.py
szyfrow/language_model_files/count_1l.txt
szyfrow/language_model_files/count_1w.txt
szyfrow/language_model_files/count_2l.txt
szyfrow/language_model_files/count_2w.txt
szyfrow/language_model_files/count_3l.txt
szyfrow/language_model_files/count_big.txt
szyfrow/language_model_files/words.txt
szyfrow/support/__init__.py
szyfrow/support/language_models.py
szyfrow/support/norms.py
szyfrow/support/plot_frequency_histogram.py
szyfrow/support/segment.py
szyfrow/support/text_prettify.py
szyfrow/support/utilities.py
szyfrow-0.0.7.dist-info/LICENCE
szyfrow-0.0.7.dist-info/METADATA
szyfrow-0.0.7.dist-info/WHEEL
szyfrow-0.0.7.dist-info/top_level.txt
szyfrow-0.0.7.dist-info/RECORD
