Metadata-Version: 2.1
Name: szyfrow
Version: 0.0.7
Summary: Tools for using and breaking simple ciphers
Home-page: https://github.com/NeilNjae/szyfrow
Author: Neil Smith
Author-email: neil.szyfrow@njae.me.uk
License: UNKNOWN
Project-URL: Documentation, https://neilnjae.github.io/szyfrow/szyfrow/index.html
Platform: UNKNOWN
Classifier: Programming Language :: Python :: 3
Classifier: License :: OSI Approved :: MIT License
Classifier: Operating System :: OS Independent
Classifier: Development Status :: 4 - Beta
Classifier: Intended Audience :: Education
Classifier: Natural Language :: English
Classifier: Topic :: Security :: Cryptography
Requires-Python: >=3.7
